MLHelper/__init__.py
MLHelper/_helper_functions.py
MLHelper/_image_label_reader/CheckDataSetsForMissingLabels.py
MLHelper/_image_label_reader/CheckDataSetsLabels.py
MLHelper/_image_label_reader/CheckDataSetsLabels200x150.py
MLHelper/_image_label_reader/ImageBatch.py
MLHelper/_image_label_reader/ImageLabelReader.py
MLHelper/_image_label_reader/ImageReader.py
MLHelper/_image_label_reader/LabelObjects.py
MLHelper/_image_label_reader/LabelReader.py
MLHelper/_image_label_reader/NoiseDatasetCopy.py
MLHelper/_image_label_reader/PathImageFinder.py
MLHelper/_image_label_reader/PathImageFinderFilterLabels.py
MLHelper/_image_label_reader/ReaderTestImages.py
MLHelper/_image_label_reader/ReaderTestSet.py
MLHelper/_image_label_reader/TestImageLabelReader.py
MLHelper/_image_label_reader/TestImageReader.py
MLHelper/_image_label_reader/TestPathImageFinder.py
MLHelper/_image_label_reader/VerifyImageReader.py
MLHelper/_image_label_reader/VerifyLabels.py
MLHelper/_image_label_reader/__init__.py
MLHelper/_util/__init__.py
MLHelper/_util/heatmap.py
MLHelper/datasets/__init__.py
MLHelper/datasets/bitbots.py
MLHelper/datasets/imagetagger.py
MLHelper/datasets/bitbots/__init__.py
MLHelper/datasets/bitbots/_bitbots.py
MLHelper/dir/__init__.py
MLHelper/dir/_clean.py
MLHelper/heatmap/__init__.py
MLHelper/heatmap/_labels.py
MLHelper/heatmap/_metrics.py
MLHelper/heatmap/_normalize.py
MLHelper/heatmap/_threshold.py
MLHelper/heatmap/metrics.py
MLHelper/heatmap/normalize.py
MLHelper/heatmap/threshold.py
MLHelper/img/__init__.py
MLHelper/img/_stack.py
MLHelper/noise/__init__.py
MLHelper/noise/_image.py
MLHelper/util/__init__.py
MLHelper/util/heatmap.py
MLHelper-0.3.5.dist-info/METADATA
MLHelper-0.3.5.dist-info/WHEEL
MLHelper-0.3.5.dist-info/top_level.txt
MLHelper-0.3.5.dist-info/RECORD
