Metadata-Version: 2.1
Name: MLHelper
Version: 0.3.5
Summary: Collection of image/label readers and useful helper methods, mostly for manipulating arrays.
Home-page: https://github.com/Daniel451/MLHelper
Author: Daniel Speck
Author-email: daniel451@mailbox.org
License: None
Platform: UNKNOWN
Requires-Python: >=3.6
Requires-Dist: numpy
Requires-Dist: scipy
Requires-Dist: tqdm
Requires-Dist: bs4
Requires-Dist: requests
